{"name": "0313-1-6040", "path": "clips/0313-1/6040/20.jpg"}
{"name": "0313-1-5320", "path": "clips/0313-1/5320/20.jpg"}
{"name": "0313-1-23700", "path": "clips/0313-1/23700/20.jpg"}
{"name": "0313-1-51660", "path": "clips/0313-1/51660/20.jpg"}
{"name": "0313-1-25680", "path": "clips/0313-1/25680/20.jpg"}
{"name": "0313-1-36000", "path": "clips/0313-1/36000/20.jpg"}
{"name": "0313-1-9460", "path": "clips/0313-1/9460/20.jpg"}
{"name": "0313-1-6180", "path": "clips/0313-1/6180/20.jpg"}
{"name": "0313-1-10100", "path": "clips/0313-1/10100/20.jpg"}
{"name": "0313-1-39720", "path": "clips/0313-1/39720/20.jpg"}
{"name": "0313-1-7780", "path": "clips/0313-1/7780/20.jpg"}
{"name": "0313-1-31680", "path": "clips/0313-1/31680/20.jpg"}
{"name": "0313-1-11980", "path": "clips/0313-1/11980/20.jpg"}
{"name": "0313-1-3300", "path": "clips/0313-1/3300/20.jpg"}
{"name": "0313-1-32520", "path": "clips/0313-1/32520/20.jpg"}
{"name": "0313-1-47160", "path": "clips/0313-1/47160/20.jpg"}
{"name": "0313-1-15220", "path": "clips/0313-1/15220/20.jpg"}
{"name": "0313-1-19320", "path": "clips/0313-1/19320/20.jpg"}
{"name": "0313-1-9600", "path": "clips/0313-1/9600/20.jpg"}